apig_wsgi/__init__.py
apig_wsgi/compat.py
apig_wsgi/py.typed
apig_wsgi-2.18.0.dist-info/LICENSE
apig_wsgi-2.18.0.dist-info/METADATA
apig_wsgi-2.18.0.dist-info/WHEEL
apig_wsgi-2.18.0.dist-info/top_level.txt
apig_wsgi-2.18.0.dist-info/RECORD
