Metadata-Version: 2.1
Name: apig_wsgi
Version: 2.18.0
Summary: Wrap a WSGI application in an AWS Lambda handler function for running on API Gateway or an ALB.
Home-page: https://github.com/adamchainz/apig-wsgi
Author: Adam Johnson
Author-email: me@adamj.eu
License: MIT
Project-URL: Changelog, https://github.com/adamchainz/apig-wsgi/blob/main/CHANGELOG.rst
Project-URL: Mastodon, https://fosstodon.org/@adamchainz
Project-URL: Twitter, https://twitter.com/adamchainz
Keywords: AWS,Lambda,API Gateway,APIG
Classifier: Development Status :: 5 - Production/Stable
Classifier: Intended Audience :: Developers
Classifier: License :: OSI Approved :: MIT License
Classifier: Natural Language :: English
Classifier: Operating System :: OS Independent
Classifier: Programming Language :: Python :: 3
Classifier: Programming Language :: Python :: 3 :: Only
Classifier: Programming Language :: Python :: 3.8
Classifier: Programming Language :: Python :: 3.9
Classifier: Programming Language :: Python :: 3.10
Classifier: Programming Language :: Python :: 3.11
Classifier: Programming Language :: Python :: 3.12
Classifier: Typing :: Typed
Requires-Python: >=3.8
License-File: LICENSE
